raula/__init__.py
raula/__main__.py
raula/agent.py
raula/aws.py
raula/aws_iot.py
raula/aws_s3.py
raula/camera.py
raula/heartbeats.py
raula/ibs_th1.py
raula/module.py
raula/periodic.py
raula/reloader.py
raula/sensehat.py
raula/sensor.py
raula/thingsboard.py
raula/utils.py
raula-0.1.dist-info/DESCRIPTION.rst
raula-0.1.dist-info/METADATA
raula-0.1.dist-info/RECORD
raula-0.1.dist-info/WHEEL
raula-0.1.dist-info/metadata.json
raula-0.1.dist-info/top_level.txt
