Metadata-Version: 2.0
Name: raula
Version: 0.1
Summary: A safety box for cyclists
Home-page: http://github.com/faermanj/RaulA
Author: Julio Faerman
Author-email: jfaerman@gmail.com
License: MIT
Platform: UNKNOWN
